README.md
setup.cfg
setup.py
kervi/devices/__init__.py
kervi/devices/version.py
kervi/devices/displays/HD44780.py
kervi/devices/displays/HD44780RGB_MCP23017.py
kervi/devices/displays/HD44780_PCF8574.py
kervi/devices/displays/SSD1306.py
kervi/devices/displays/__init__.py
kervi/devices/displays/dummy_display_driver.py
kervi/devices/gpio/ADS1X15.py
kervi/devices/gpio/MCP230XX.py
kervi/devices/gpio/PCF8574.py
kervi/devices/gpio/PCF8591.py
kervi/devices/gpio/__init__.py
kervi/devices/gpio/dummy_gpio.py
kervi/devices/motors/LN298.py
kervi/devices/motors/PCA9685_i2c_servo.py
kervi/devices/motors/__init__.py
kervi/devices/motors/adafruit_i2c_motor_hat.py
kervi/devices/motors/dummy_motor_driver.py
kervi/devices/motors/grove_i2c_motor_driver.py
kervi/devices/pwm/PCA9685.py
kervi/devices/pwm/__init__.py
kervi/devices/sensors/BMP085.py
kervi/devices/sensors/CW2015.py
kervi/devices/sensors/DS18XXX.py
kervi/devices/sensors/LSM9DS0.py
kervi/devices/sensors/LSM9DS1.py
kervi/devices/sensors/TCS34725.py
kervi/devices/sensors/TSL2561.py
kervi/devices/sensors/VL6180X.py
kervi/devices/sensors/__init__.py
kervi/devices/sensors/dummy_sensor.py
kervi/devices/sensors/system.py
kervi/devices/__init__.py
kervi/devices/version.py
kervi/devices/displays/HD44780.py
kervi/devices/displays/HD44780RGB_MCP23017.py
kervi/devices/displays/HD44780_PCF8574.py
kervi/devices/displays/SSD1306.py
kervi/devices/displays/__init__.py
kervi/devices/displays/dummy_display_driver.py
kervi/devices/gpio/ADS1X15.py
kervi/devices/gpio/MCP230XX.py
kervi/devices/gpio/PCF8574.py
kervi/devices/gpio/PCF8591.py
kervi/devices/gpio/__init__.py
kervi/devices/gpio/dummy_gpio.py
kervi/devices/motors/LN298.py
kervi/devices/motors/PCA9685_i2c_servo.py
kervi/devices/motors/__init__.py
kervi/devices/motors/adafruit_i2c_motor_hat.py
kervi/devices/motors/dummy_motor_driver.py
kervi/devices/motors/grove_i2c_motor_driver.py
kervi/devices/pwm/PCA9685.py
kervi/devices/pwm/__init__.py
kervi/devices/sensors/BMP085.py
kervi_device_library.egg-info/PKG-INFO
kervi_device_library.egg-info/SOURCES.txt
kervi_device_library.egg-info/dependency_links.txt
kervi_device_library.egg-info/requires.txt
kervi_device_library.egg-info/top_level.txt