Metadata-Version: 1.0
Name: kervi-device-library
Version: 0.21.5
Summary: Hardware component library for the Kervi automation framework
Home-page: https://github.com/kervi/kervi-components
Author: Tim Wentzlau
Author-email: tim.wentzlau@gmail.com
License: UNKNOWN
Platform: UNKNOWN
